{"version":1,"resource":"file:///c%3A/Users/Asus/Desktop/Bootcamp/ejercicios.html","entries":[{"id":"LgU3.html","timestamp":1661910393698},{"id":"STnx.html","timestamp":1661910684957},{"id":"8XWU.html","timestamp":1661910818213},{"id":"FF6A.html","timestamp":1661910850101},{"id":"rAGL.html","timestamp":1661911257561},{"id":"GC0r.html","timestamp":1661911292345},{"id":"oquV.html","timestamp":1661911346593},{"id":"RuGK.html","timestamp":1661911375768},{"id":"LwvS.html","timestamp":1661911395913},{"id":"PGc6.html","timestamp":1661911589277},{"id":"OpAW.html","timestamp":1661911606081},{"id":"SIIH.html","timestamp":1661911792866},{"id":"7hQ7.html","timestamp":1661911889078},{"id":"YD44.html","timestamp":1661911912346},{"id":"eGtR.html","timestamp":1661911960091},{"id":"CfkF.html","timestamp":1661911971574},{"id":"72Z3.html","timestamp":1661911998235},{"id":"CnkA.html","timestamp":1661912038258},{"id":"pDku.html","timestamp":1661912204152},{"id":"dpI7.html","timestamp":1661912230128},{"id":"MfLw.html","timestamp":1661912286178},{"id":"fyKx.html","timestamp":1661912388033},{"id":"FkBC.html","timestamp":1661912420003},{"id":"2WjE.html","timestamp":1661912463066},{"id":"T4zi.html","timestamp":1661912542184},{"id":"CGBx.html","timestamp":1661912593698},{"id":"Kbb2.html","timestamp":1661912652530},{"id":"Vb1I.html","timestamp":1661912721258},{"id":"woKv.html","timestamp":1661912748283},{"id":"tcIO.html","timestamp":1661913047996},{"id":"b1VQ.html","timestamp":1661913067926},{"id":"VN6z.html","timestamp":1661913148014},{"id":"uBZG.html","timestamp":1661913180241},{"id":"uFIp.html","timestamp":1661913218458},{"id":"O0pB.html","timestamp":1661913282459},{"id":"BcGC.html","timestamp":1661913313166},{"id":"sIb6.html","timestamp":1661913327242},{"id":"3UXP.html","timestamp":1661913337252},{"id":"YAnz.html","source":"undoRedo.source","timestamp":1661913348686},{"id":"YmF1.html","timestamp":1661913366609},{"id":"H8rT.html","timestamp":1661913454164},{"id":"Dg5u.html","timestamp":1661913499818},{"id":"z5KZ.html","timestamp":1661913558507},{"id":"4P3l.html","timestamp":1661913590590},{"id":"zca0.html","timestamp":1661913617204},{"id":"7TOt.html","timestamp":1661913634024},{"id":"OaCP.html","timestamp":1661913655006},{"id":"iQuu.html","timestamp":1661913675293},{"id":"bi0g.html","timestamp":1661913702152},{"id":"oKD3.html","timestamp":1661913737556}]}